django_loginas-0.3.14.dist-info/licenses/LICENSE
loginas/__init__.py
loginas/context_processors.py
loginas/settings.py
loginas/urls.py
loginas/utils.py
loginas/views.py
loginas/locale/de/LC_MESSAGES/django.mo
loginas/locale/de/LC_MESSAGES/django.po
loginas/locale/fa/LC_MESSAGES/django.mo
loginas/locale/fa/LC_MESSAGES/django.po
loginas/locale/fr/LC_MESSAGES/django.mo
loginas/locale/fr/LC_MESSAGES/django.po
loginas/locale/pl/LC_MESSAGES/django.mo
loginas/locale/pl/LC_MESSAGES/django.po
loginas/templates/admin/auth/user/change_form.html
loginas/templates/loginas/change_form.html
loginas/templates/loginas/javascript.html
loginas/templates/loginas/modal.html
loginas/templatetags/__init__.py
loginas/templatetags/loginas_javascript.py
loginas/tests/__init__.py
loginas/tests/manage.py
loginas/tests/models.py
loginas/tests/settings.py
loginas/tests/tests.py
loginas/tests/urls.py
loginas/tests/views.py
django_loginas-0.3.14.dist-info/METADATA
django_loginas-0.3.14.dist-info/WHEEL
django_loginas-0.3.14.dist-info/top_level.txt
django_loginas-0.3.14.dist-info/RECORD
